niar-0.1.1.dist-info/METADATA
niar-0.1.1.dist-info/WHEEL
niar-0.1.1.dist-info/licenses/LICENSE
niar/__init__.py
niar/build.py
niar/cmdrunner.py
niar/cxxrtl.py
niar/cxxrtl_platform.py
niar/logging.py
niar/project.py
niar-0.1.1.dist-info/RECORD
